ffpass/__init__.py
ffpass-0.5.0.dist-info/LICENSE
ffpass-0.5.0.dist-info/METADATA
ffpass-0.5.0.dist-info/WHEEL
ffpass-0.5.0.dist-info/entry_points.txt
ffpass-0.5.0.dist-info/top_level.txt
ffpass-0.5.0.dist-info/RECORD
