Metadata-Version: 2.1
Name: ffpass
Version: 0.5.0
Summary: Import and Export passwords for Firefox
Home-page: https://github.com/louisabraham/ffpass
Author: Louis Abraham
Author-email: louis.abraham@yahoo.fr
License: MIT
Platform: UNKNOWN
Classifier: Topic :: Utilities
Classifier: Topic :: Security :: Cryptography
Requires-Python: >=3.6
Requires-Dist: pyasn1
Requires-Dist: pycryptodome
